{
  "table_of_contents": [
    {
      "title": "Termodin\u00b4amica, 1-2025",
      "heading_level": null,
      "page_id": 0,
      "polygon": [
        [
          158.98899841308594,
          334.04083013534546
        ],
        [
          383.62724447250366,
          334.04083013534546
        ],
        [
          383.62724447250366,
          356.8477005958557
        ],
        [
          158.98899841308594,
          356.8477005958557
        ]
      ]
    },
    {
      "title": "Prefacio",
      "heading_level": null,
      "page_id": 2,
      "polygon": [
        [
          56.287945210933685,
          156.3271484375
        ],
        [
          157.06522250175476,
          156.3271484375
        ],
        [
          155.91575622558594,
          181.1142578125
        ],
        [
          55.092632710933685,
          181.1142578125
        ]
      ]
    },
    {
      "title": "\u00b4\nIndice general",
      "heading_level": null,
      "page_id": 3,
      "polygon": [
        [
          54.91400146484375,
          150.33709716796875
        ],
        [
          228.9811728000641,
          150.33709716796875
        ],
        [
          227.7858603000641,
          181.89726161956787
        ],
        [
          54.402167201042175,
          181.89726161956787
        ]
      ]
    },
    {
      "title": "Cap\u00b4\u0131tulo 1",
      "heading_level": null,
      "page_id": 5,
      "polygon": [
        [
          56.410415679216385,
          154.569580078125
        ],
        [
          163.4561309814453,
          154.569580078125
        ],
        [
          163.4561309814453,
          175.7656191587448
        ],
        [
          55.215103179216385,
          175.7656191587448
        ]
      ]
    },
    {
      "title": "Introducci\u00b4on y Ley cero de la\ntermodin\u00b4amica.",
      "heading_level": null,
      "page_id": 5,
      "polygon": [
        [
          55.262884855270386,
          201.1590576171875
        ],
        [
          417.42064905166626,
          201.1590576171875
        ],
        [
          417.42064905166626,
          255.83416748046875
        ],
        [
          55.262884855270386,
          255.83416748046875
        ]
      ]
    },
    {
      "title": "1.1. Introducci\u00b4on",
      "heading_level": null,
      "page_id": 5,
      "polygon": [
        [
          56.29213106632233,
          296.98992919921875
        ],
        [
          187.57337951660156,
          296.98992919921875
        ],
        [
          187.57337951660156,
          311.33612060546875
        ],
        [
          56.29213106632233,
          311.33612060546875
        ]
      ]
    },
    {
      "title": "1.2. Definiciones e ideas fundamentales:",
      "heading_level": null,
      "page_id": 5,
      "polygon": [
        [
          56.02413600683212,
          636.2779998779297
        ],
        [
          346.74940252304077,
          636.2779998779297
        ],
        [
          346.74940252304077,
          650.6241912841797
        ],
        [
          56.02413600683212,
          650.98597240448
        ]
      ]
    },
    {
      "title": "1.2.1. Sistema y su entorno",
      "heading_level": null,
      "page_id": 5,
      "polygon": [
        [
          56.6929931640625,
          663.2466430664062
        ],
        [
          225.3149471282959,
          663.2466430664062
        ],
        [
          225.2374267578125,
          675.2018356323242
        ],
        [
          55.55417114496231,
          676.0692529678345
        ]
      ]
    },
    {
      "title": "1.2.2. Medio Continuo",
      "heading_level": null,
      "page_id": 7,
      "polygon": [
        [
          56.692996978759766,
          300.81226229667664
        ],
        [
          197.01272821426392,
          300.81226229667664
        ],
        [
          196.55690002441406,
          313.2338562011719
        ],
        [
          56.32367545366287,
          313.2338562011719
        ]
      ]
    },
    {
      "title": "1.2.3. Estado y proceso Termodinamico",
      "heading_level": null,
      "page_id": 7,
      "polygon": [
        [
          55.77930450439453,
          609.0496215820312
        ],
        [
          297.64200496673584,
          609.0496215820312
        ],
        [
          297.64200496673584,
          621.0048217773438
        ],
        [
          55.77930450439453,
          621.9560551643372
        ]
      ]
    },
    {
      "title": "",
      "heading_level": null,
      "page_id": 8,
      "polygon": [
        [
          7.799272254109383,
          247.30423307418823
        ],
        [
          49.58695614337921,
          247.30423307418823
        ],
        [
          48.39164364337921,
          256.9199438095093
        ],
        [
          6.603959754109383,
          256.9199438095093
        ]
      ]
    },
    {
      "title": "Tipos de Procesos",
      "heading_level": null,
      "page_id": 8,
      "polygon": [
        [
          56.692996978759766,
          285.0841979980469
        ],
        [
          157.76228141784668,
          285.0841979980469
        ],
        [
          157.76228141784668,
          295.9933166503906
        ],
        [
          56.692996978759766,
          295.9933166503906
        ]
      ]
    },
    {
      "title": "1.3. Presi\u00b4on",
      "heading_level": null,
      "page_id": 8,
      "polygon": [
        [
          56.6929931640625,
          657.4989776611328
        ],
        [
          151.75770378112793,
          657.4989776611328
        ],
        [
          150.71798706054688,
          671.8451843261719
        ],
        [
          55.78406944870949,
          672.3493509292603
        ]
      ]
    },
    {
      "title": "1.3.1. Man\u00b4ometro",
      "heading_level": null,
      "page_id": 10,
      "polygon": [
        [
          56.33574512600899,
          297.4427490234375
        ],
        [
          170.6264637708664,
          297.4427490234375
        ],
        [
          169.71751403808594,
          309.39794921875
        ],
        [
          55.14043262600899,
          309.39794921875
        ]
      ]
    },
    {
      "title": "1.4. Temperatura y Ley cero",
      "heading_level": null,
      "page_id": 10,
      "polygon": [
        [
          55.25088357925415,
          616.8509979248047
        ],
        [
          268.8158874511719,
          616.8509979248047
        ],
        [
          268.8158874511719,
          631.1971893310547
        ],
        [
          55.25088357925415,
          631.1971893310547
        ]
      ]
    },
    {
      "title": "1.4.1. Ley cero de termodin\u00b4amica",
      "heading_level": null,
      "page_id": 11,
      "polygon": [
        [
          56.26112473011017,
          86.65460205078125
        ],
        [
          263.1011470556259,
          86.65460205078125
        ],
        [
          261.92791748046875,
          98.60980224609375
        ],
        [
          55.06581223011017,
          98.60980224609375
        ]
      ]
    },
    {
      "title": "1.4.2. Temperatura",
      "heading_level": null,
      "page_id": 11,
      "polygon": [
        [
          56.04323226213455,
          327.6486511230469
        ],
        [
          179.34951281547546,
          327.6486511230469
        ],
        [
          179.34951281547546,
          339.6038513183594
        ],
        [
          56.04323226213455,
          339.6038513183594
        ]
      ]
    },
    {
      "title": "1.4.3. Term\u00b4ometro de gas a Volumen constante",
      "heading_level": null,
      "page_id": 11,
      "polygon": [
        [
          55.70792609453201,
          431.50067138671875
        ],
        [
          343.2884752750397,
          431.50067138671875
        ],
        [
          343.2884752750397,
          443.45587158203125
        ],
        [
          55.70792609453201,
          443.45587158203125
        ]
      ]
    },
    {
      "title": "1.4.4. Escala Celsius y Kelvin",
      "heading_level": null,
      "page_id": 12,
      "polygon": [
        [
          56.4332372546196,
          277.12164306640625
        ],
        [
          240.111243724823,
          277.12164306640625
        ],
        [
          238.95005798339844,
          289.07684326171875
        ],
        [
          55.2379247546196,
          289.07684326171875
        ]
      ]
    },
    {
      "title": "1.5. Expansi\u00b4on termica de solidos y liquidos",
      "heading_level": null,
      "page_id": 12,
      "polygon": [
        [
          56.39892053604126,
          434.19000244140625
        ],
        [
          378.5995123386383,
          434.19000244140625
        ],
        [
          377.4041998386383,
          448.53619384765625
        ],
        [
          55.20360803604126,
          448.53619384765625
        ]
      ]
    },
    {
      "title": "1.5.1. Comportamiento an\u00b4omalo del agua",
      "heading_level": null,
      "page_id": 13,
      "polygon": [
        [
          56.26132535934448,
          264.1475830078125
        ],
        [
          308.45157980918884,
          264.1475830078125
        ],
        [
          307.94378662109375,
          276.13493728637695
        ],
        [
          55.06601285934448,
          276.13493728637695
        ]
      ]
    },
    {
      "title": "1.6. Ejemplos Resueltos",
      "heading_level": null,
      "page_id": 13,
      "polygon": [
        [
          56.692996978759766,
          616.8509826660156
        ],
        [
          236.32770466804504,
          616.8509826660156
        ],
        [
          235.13239216804504,
          631.1971740722656
        ],
        [
          56.30007416009903,
          631.5958886146545
        ]
      ]
    },
    {
      "title": "Soluci\u00b4on",
      "heading_level": null,
      "page_id": 15,
      "polygon": [
        [
          71.86235493421555,
          527.1502380371094
        ],
        [
          115.57459527254105,
          526.9157681465149
        ],
        [
          115.57459527254105,
          538.0593566894531
        ],
        [
          71.86235493421555,
          538.3299193382263
        ]
      ]
    },
    {
      "title": "Cap\u00b4\u0131tulo 2",
      "heading_level": null,
      "page_id": 17,
      "polygon": [
        [
          56.58787223696709,
          154.569580078125
        ],
        [
          163.78106725215912,
          154.569580078125
        ],
        [
          163.4561309814453,
          175.2320556640625
        ],
        [
          55.39255973696709,
          175.2320556640625
        ]
      ]
    },
    {
      "title": "Energ\u00b4\u0131a y Calor",
      "heading_level": null,
      "page_id": 17,
      "polygon": [
        [
          55.63478761911392,
          201.1590576171875
        ],
        [
          249.75970458984375,
          201.1590576171875
        ],
        [
          249.75970458984375,
          226.97742319107056
        ],
        [
          55.63478761911392,
          226.97742319107056
        ]
      ]
    },
    {
      "title": "2.1. Formas de energ\u00b4\u0131a",
      "heading_level": null,
      "page_id": 17,
      "polygon": [
        [
          55.89742040634155,
          267.1029052734375
        ],
        [
          227.32102060317993,
          267.1029052734375
        ],
        [
          227.32102060317993,
          281.4491271972656
        ],
        [
          55.89742040634155,
          281.4491271972656
        ]
      ]
    },
    {
      "title": "2.1.1. Energ\u00b4\u0131a Mec\u00b4anica",
      "heading_level": null,
      "page_id": 18,
      "polygon": [
        [
          56.27223229408264,
          222.54962158203125
        ],
        [
          207.3549646139145,
          222.4278838634491
        ],
        [
          206.1596521139145,
          234.50482177734375
        ],
        [
          55.07691979408264,
          235.10505509376526
        ]
      ]
    },
    {
      "title": "2.2. Transferencia de energ\u00b4\u0131a",
      "heading_level": null,
      "page_id": 18,
      "polygon": [
        [
          56.07878923416138,
          616.8510131835938
        ],
        [
          270.1761910915375,
          616.5866975784302
        ],
        [
          269.9205627441406,
          631.1972045898438
        ],
        [
          54.88347673416138,
          631.9807662963867
        ]
      ]
    },
    {
      "title": "2.3. Transferencia de energ\u00b4\u0131a por calor",
      "heading_level": null,
      "page_id": 19,
      "polygon": [
        [
          55.86983388662338,
          237.739013671875
        ],
        [
          338.8683776855469,
          237.739013671875
        ],
        [
          338.8683776855469,
          252.15898847579956
        ],
        [
          55.86983388662338,
          252.15898847579956
        ]
      ]
    },
    {
      "title": "Capacidad calor\u00b4\u0131fica y calorimetria",
      "heading_level": null,
      "page_id": 20,
      "polygon": [
        [
          56.53784716129303,
          87.47216796875
        ],
        [
          247.8362352848053,
          87.47216796875
        ],
        [
          247.71133422851562,
          98.38128662109375
        ],
        [
          55.34253466129303,
          98.38128662109375
        ]
      ]
    },
    {
      "title": "2.3.1. Mecanismos de transferencia de calor",
      "heading_level": null,
      "page_id": 20,
      "polygon": [
        [
          56.12612861394882,
          505.87261962890625
        ],
        [
          321.75177001953125,
          505.87261962890625
        ],
        [
          321.75177001953125,
          517.8278198242188
        ],
        [
          54.93081611394882,
          517.8278198242188
        ]
      ]
    },
    {
      "title": "Conducci\u00b4on t\u00b4ermica",
      "heading_level": null,
      "page_id": 20,
      "polygon": [
        [
          56.41825845837593,
          570.1431732177734
        ],
        [
          166.98112177848816,
          570.1431732177734
        ],
        [
          166.32949829101562,
          581.1653938293457
        ],
        [
          55.22294595837593,
          581.1653938293457
        ]
      ]
    },
    {
      "title": "Convecci\u00b4on",
      "heading_level": null,
      "page_id": 21,
      "polygon": [
        [
          55.83442282676697,
          425.96069526672363
        ],
        [
          118.50398254394531,
          425.96069526672363
        ],
        [
          118.50398254394531,
          436.8792724609375
        ],
        [
          55.83442282676697,
          436.8792724609375
        ]
      ]
    },
    {
      "title": "Radiaci\u00b4on",
      "heading_level": null,
      "page_id": 21,
      "polygon": [
        [
          55.82457375526428,
          572.7931976318359
        ],
        [
          111.47051453590393,
          572.7931976318359
        ],
        [
          111.47051453590393,
          583.7023010253906
        ],
        [
          55.82457375526428,
          583.7023010253906
        ]
      ]
    },
    {
      "title": "2.4. Forma Mec\u00b4anica del trabajo",
      "heading_level": null,
      "page_id": 22,
      "polygon": [
        [
          54.845375418663025,
          400.7460021972656
        ],
        [
          297.0492858886719,
          400.7460021972656
        ],
        [
          297.0492858886719,
          415.0921936035156
        ],
        [
          54.845375418663025,
          415.0921936035156
        ]
      ]
    },
    {
      "title": "2.4.1. Trabajo del Resorte",
      "heading_level": null,
      "page_id": 22,
      "polygon": [
        [
          55.127806663513184,
          516.4966430664062
        ],
        [
          219.20697247982025,
          516.4966430664062
        ],
        [
          219.20697247982025,
          528.4518432617188
        ],
        [
          55.127806663513184,
          528.4518432617188
        ]
      ]
    },
    {
      "title": "2.4.2. Trabajo de Flecha",
      "heading_level": null,
      "page_id": 22,
      "polygon": [
        [
          55.03495180606842,
          601.8496246337891
        ],
        [
          209.26626813411713,
          601.7806849479675
        ],
        [
          209.26626813411713,
          613.8048248291016
        ],
        [
          55.03495180606842,
          614.0685410499573
        ]
      ]
    },
    {
      "title": "2.5. Transferencia de energ\u00b4\u0131a por trabajo",
      "heading_level": null,
      "page_id": 23,
      "polygon": [
        [
          55.39889323711395,
          202.2789306640625
        ],
        [
          357.03854513168335,
          202.2789306640625
        ],
        [
          357.03854513168335,
          216.62518310546875
        ],
        [
          55.39889323711395,
          216.62518310546875
        ]
      ]
    },
    {
      "title": "Trabajo El\u00b4ectrico",
      "heading_level": null,
      "page_id": 24,
      "polygon": [
        [
          56.692996978759766,
          87.47216796875
        ],
        [
          153.5906707048416,
          87.47216796875
        ],
        [
          152.3953582048416,
          98.38128662109375
        ],
        [
          55.64012709259987,
          98.38128662109375
        ]
      ]
    },
    {
      "title": "2.6. Primera Ley de Termodin\u00b4amica",
      "heading_level": null,
      "page_id": 24,
      "polygon": [
        [
          56.27611720561981,
          344.3960876464844
        ],
        [
          323.97761964797974,
          344.3960876464844
        ],
        [
          322.78230714797974,
          358.7422790527344
        ],
        [
          55.08080470561981,
          358.7422790527344
        ]
      ]
    },
    {
      "title": "2.7. Ejemplos",
      "heading_level": null,
      "page_id": 26,
      "polygon": [
        [
          56.34644231200218,
          84.78594970703125
        ],
        [
          163.1746015548706,
          84.78594970703125
        ],
        [
          162.08016967773438,
          99.1322021484375
        ],
        [
          55.15112981200218,
          99.1322021484375
        ]
      ]
    },
    {
      "title": "2.8. Problemas propuestos",
      "heading_level": null,
      "page_id": 30,
      "polygon": [
        [
          55.75613182783127,
          350.5690002441406
        ],
        [
          253.33639526367188,
          350.5690002441406
        ],
        [
          253.33639526367188,
          364.9151916503906
        ],
        [
          55.75613182783127,
          364.9151916503906
        ]
      ]
    },
    {
      "title": "Cap\u00b4\u0131tulo 3",
      "heading_level": null,
      "page_id": 31,
      "polygon": [
        [
          56.46244704723358,
          154.569580078125
        ],
        [
          164.08996331691742,
          154.569580078125
        ],
        [
          163.4561309814453,
          175.2320556640625
        ],
        [
          55.26713454723358,
          175.2320556640625
        ]
      ]
    },
    {
      "title": "Sustancias puras",
      "heading_level": null,
      "page_id": 31,
      "polygon": [
        [
          55.837094843387604,
          201.1590576171875
        ],
        [
          259.3275451660156,
          201.1590576171875
        ],
        [
          259.3275451660156,
          225.9461669921875
        ],
        [
          55.837094843387604,
          225.9461669921875
        ]
      ]
    },
    {
      "title": "3.1. Tipos de sustancias",
      "heading_level": null,
      "page_id": 31,
      "polygon": [
        [
          56.15307676792145,
          324.7200012207031
        ],
        [
          235.1115996837616,
          324.7200012207031
        ],
        [
          235.10231018066406,
          339.0661926269531
        ],
        [
          54.95776426792145,
          339.0661926269531
        ]
      ]
    },
    {
      "title": "3.2. Fases de una Sustancia Pura",
      "heading_level": null,
      "page_id": 31,
      "polygon": [
        [
          56.260641396045685,
          465.6180419921875
        ],
        [
          300.0683784484863,
          465.6180419921875
        ],
        [
          299.4593811035156,
          479.9642333984375
        ],
        [
          55.065328896045685,
          479.9642333984375
        ]
      ]
    },
    {
      "title": "3.2.1. Cambios de Fase en sustancias puras.",
      "heading_level": null,
      "page_id": 31,
      "polygon": [
        [
          55.20930773019791,
          630.2856750488281
        ],
        [
          321.4887390136719,
          630.2856750488281
        ],
        [
          321.4887390136719,
          642.2408752441406
        ],
        [
          55.20930773019791,
          642.2408752441406
        ]
      ]
    },
    {
      "title": "3.2.2. Diagrama T-\u03bd",
      "heading_level": null,
      "page_id": 32,
      "polygon": [
        [
          55.88043987751007,
          278.95068359375
        ],
        [
          183.21098721027374,
          278.95068359375
        ],
        [
          183.21098721027374,
          290.9058837890625
        ],
        [
          55.88043987751007,
          290.9058837890625
        ]
      ]
    },
    {
      "title": "3.2.3. Diagrama P \u2212 v",
      "heading_level": null,
      "page_id": 34,
      "polygon": [
        [
          56.048448622226715,
          394.12969970703125
        ],
        [
          194.04826712608337,
          394.12969970703125
        ],
        [
          192.85295462608337,
          406.2398376464844
        ],
        [
          54.853136122226715,
          406.2398376464844
        ]
      ]
    },
    {
      "title": "3.2.4. Incluyendo Solidos",
      "heading_level": null,
      "page_id": 34,
      "polygon": [
        [
          55.49667263031006,
          607.4016723632812
        ],
        [
          211.97738921642303,
          607.4016723632812
        ],
        [
          211.97738921642303,
          619.3568725585938
        ],
        [
          55.49667263031006,
          619.3568725585938
        ]
      ]
    },
    {
      "title": "3.2.5. La superficie P-V-T",
      "heading_level": null,
      "page_id": 35,
      "polygon": [
        [
          56.563792169094086,
          621.0956420898438
        ],
        [
          218.32673907279968,
          620.9714612960815
        ],
        [
          218.24362182617188,
          633.0508422851562
        ],
        [
          55.368479669094086,
          633.5883493423462
        ]
      ]
    },
    {
      "title": "3.3. Tablas de Propiedades",
      "heading_level": null,
      "page_id": 36,
      "polygon": [
        [
          53.80526787042618,
          595.4861669540405
        ],
        [
          256.2773132324219,
          595.4861669540405
        ],
        [
          256.2773132324219,
          615.2281951904297
        ],
        [
          53.80526787042618,
          615.2281951904297
        ]
      ]
    },
    {
      "title": "3.3.1. Estados de liquido Saturado y Vapor Saturado",
      "heading_level": null,
      "page_id": 37,
      "polygon": [
        [
          55.424792647361755,
          267.68267822265625
        ],
        [
          376.0446267127991,
          267.68267822265625
        ],
        [
          376.0446267127991,
          279.63787841796875
        ],
        [
          55.424792647361755,
          279.63787841796875
        ]
      ]
    },
    {
      "title": "3.3.2. Mezcla de liquido-gas saturado",
      "heading_level": null,
      "page_id": 39,
      "polygon": [
        [
          56.02548569440842,
          554.0816192626953
        ],
        [
          283.3397216796875,
          554.0816192626953
        ],
        [
          283.3397216796875,
          566.0368194580078
        ],
        [
          54.83017319440842,
          566.0368194580078
        ]
      ]
    },
    {
      "title": "3.3.3. Vapor Sobrecalentado",
      "heading_level": null,
      "page_id": 43,
      "polygon": [
        [
          56.08602100610733,
          86.65460205078125
        ],
        [
          231.7498197555542,
          86.65460205078125
        ],
        [
          230.5545072555542,
          98.60980224609375
        ],
        [
          54.89070850610733,
          98.60980224609375
        ]
      ]
    },
    {
      "title": "siguiente:",
      "heading_level": null,
      "page_id": 43,
      "polygon": [
        [
          56.692996978759766,
          515.2621459960938
        ],
        [
          102.83675462007523,
          514.4232702255249
        ],
        [
          101.64144212007523,
          526.1712646484375
        ],
        [
          56.692996978759766,
          526.1712646484375
        ]
      ]
    },
    {
      "title": "3.4. Liquido Comprimido",
      "heading_level": null,
      "page_id": 44,
      "polygon": [
        [
          55.63896435499191,
          243.4189453125
        ],
        [
          245.8565354347229,
          243.4189453125
        ],
        [
          245.8565354347229,
          257.76519775390625
        ],
        [
          55.63896435499191,
          257.76519775390625
        ]
      ]
    },
    {
      "title": "3.5. Sustancias y gases ideales",
      "heading_level": null,
      "page_id": 44,
      "polygon": [
        [
          55.656811237335205,
          454.8880310058594
        ],
        [
          278.970463514328,
          454.8880310058594
        ],
        [
          278.970463514328,
          469.2342224121094
        ],
        [
          55.656811237335205,
          469.2342224121094
        ]
      ]
    },
    {
      "title": "Cap\u00b4\u0131tulo 4",
      "heading_level": null,
      "page_id": 49,
      "polygon": [
        [
          56.34248444437981,
          154.569580078125
        ],
        [
          164.6846466064453,
          154.569580078125
        ],
        [
          163.4893341064453,
          175.34191381931305
        ],
        [
          55.14717194437981,
          175.34191381931305
        ]
      ]
    },
    {
      "title": "Analisis de energias de sistemas\ncerrados",
      "heading_level": null,
      "page_id": 49,
      "polygon": [
        [
          55.74096608161926,
          201.1590576171875
        ],
        [
          446.08513140678406,
          201.1590576171875
        ],
        [
          446.08513140678406,
          255.83416748046875
        ],
        [
          55.74096608161926,
          255.83416748046875
        ]
      ]
    },
    {
      "title": "4.1. Trabajo hecho por una frontera m\u00b4ovil",
      "heading_level": null,
      "page_id": 49,
      "polygon": [
        [
          55.736698150634766,
          354.0269470214844
        ],
        [
          365.4856925010681,
          354.0269470214844
        ],
        [
          365.4856925010681,
          368.3731384277344
        ],
        [
          55.736698150634766,
          368.3731384277344
        ]
      ]
    },
    {
      "title": "4.1.1. Proceso Politropico",
      "heading_level": null,
      "page_id": 50,
      "polygon": [
        [
          55.95358747243881,
          129.339599609375
        ],
        [
          216.7838273048401,
          129.339599609375
        ],
        [
          216.7838273048401,
          141.2947998046875
        ],
        [
          55.95358747243881,
          141.2947998046875
        ]
      ]
    },
    {
      "title": "4.2. Balance de energ\u00b4\u0131a de sistema cerrado.",
      "heading_level": null,
      "page_id": 51,
      "polygon": [
        [
          56.692996978759766,
          84.78594970703125
        ],
        [
          372.36906266212463,
          84.78594970703125
        ],
        [
          372.3236999511719,
          99.1322021484375
        ],
        [
          55.57331299781799,
          99.1322021484375
        ]
      ]
    },
    {
      "title": "4.3. Calores Especificos",
      "heading_level": null,
      "page_id": 53,
      "polygon": [
        [
          56.2357177734375,
          84.78594970703125
        ],
        [
          231.70427691936493,
          84.78594970703125
        ],
        [
          231.53012084960938,
          99.1322021484375
        ],
        [
          55.0404052734375,
          99.1322021484375
        ]
      ]
    },
    {
      "title": "a) La temperatura final",
      "heading_level": null,
      "page_id": 53,
      "polygon": [
        [
          69.0260009765625,
          429.5162048339844
        ],
        [
          179.78307259082794,
          429.3568525314331
        ],
        [
          178.58776009082794,
          440.4253234863281
        ],
        [
          67.87614843249321,
          441.35854053497314
        ]
      ]
    },
    {
      "title": "4.4. Energ\u00b4\u0131a interna, Entalp\u00b4\u0131a y calores especificos de gases\nideales",
      "heading_level": null,
      "page_id": 55,
      "polygon": [
        [
          56.42669856548309,
          430.4200134277344
        ],
        [
          484.716290473938,
          430.4200134277344
        ],
        [
          484.0949401855469,
          462.6982116699219
        ],
        [
          55.23138606548309,
          462.6982116699219
        ]
      ]
    },
    {
      "title": "4.4.1. Relaciones de calores espec\u00b4\u0131ficos de gases ideales",
      "heading_level": null,
      "page_id": 56,
      "polygon": [
        [
          56.389636874198914,
          343.0287170410156
        ],
        [
          388.05604362487793,
          343.0287170410156
        ],
        [
          386.86073112487793,
          355.05048751831055
        ],
        [
          55.194324374198914,
          355.05048751831055
        ]
      ]
    },
    {
      "title": "4.4.2. Primera Ley de termodin\u00b4amica: Procesos y Ciclos",
      "heading_level": null,
      "page_id": 57,
      "polygon": [
        [
          55.67517793178558,
          308.43963623046875
        ],
        [
          397.3795394897461,
          308.43963623046875
        ],
        [
          396.1842269897461,
          320.39483642578125
        ],
        [
          54.47986543178558,
          320.39483642578125
        ]
      ]
    },
    {
      "title": "4.4.3. Proceso adiabatico en gases ideales",
      "heading_level": null,
      "page_id": 58,
      "polygon": [
        [
          56.65319985151291,
          86.65460205078125
        ],
        [
          308.15300703048706,
          86.65460205078125
        ],
        [
          307.81201171875,
          98.60980224609375
        ],
        [
          55.45788735151291,
          98.60980224609375
        ]
      ]
    },
    {
      "title": "Cap\u00b4\u0131tulo 5",
      "heading_level": null,
      "page_id": 61,
      "polygon": [
        [
          56.4013052880764,
          154.569580078125
        ],
        [
          163.4561309814453,
          154.569580078125
        ],
        [
          163.4561309814453,
          175.2320556640625
        ],
        [
          55.2059927880764,
          175.2320556640625
        ]
      ]
    },
    {
      "title": "Masa y volumen de control",
      "heading_level": null,
      "page_id": 61,
      "polygon": [
        [
          55.92410409450531,
          201.1590576171875
        ],
        [
          389.78349781036377,
          201.1590576171875
        ],
        [
          389.78349781036377,
          225.9461669921875
        ],
        [
          55.92410409450531,
          225.9461669921875
        ]
      ]
    },
    {
      "title": "5.1. Conservaci\u00b4on de la masa",
      "heading_level": null,
      "page_id": 61,
      "polygon": [
        [
          56.46572095155716,
          343.91497802734375
        ],
        [
          272.2710521221161,
          343.91497802734375
        ],
        [
          271.2404479980469,
          358.26116943359375
        ],
        [
          55.27040845155716,
          358.26116943359375
        ]
      ]
    },
    {
      "title": "5.1.1. Flujo de masa",
      "heading_level": null,
      "page_id": 61,
      "polygon": [
        [
          56.14222911000252,
          494.8306884765625
        ],
        [
          184.78118455410004,
          494.8306884765625
        ],
        [
          184.78118455410004,
          506.785888671875
        ],
        [
          56.14222911000252,
          506.785888671875
        ]
      ]
    },
    {
      "title": "5.1.2. Aplicacion al volumen de control",
      "heading_level": null,
      "page_id": 63,
      "polygon": [
        [
          55.831814646720886,
          222.82763671875
        ],
        [
          296.70143687725067,
          222.82763671875
        ],
        [
          296.70143687725067,
          234.7828369140625
        ],
        [
          55.831814646720886,
          234.7828369140625
        ]
      ]
    },
    {
      "title": "5.1.3. Balance de masa en proceso estacionario",
      "heading_level": null,
      "page_id": 64,
      "polygon": [
        [
          56.654157400131226,
          306.2035827636719
        ],
        [
          342.2402422428131,
          306.2035827636719
        ],
        [
          341.0449297428131,
          318.1587829589844
        ],
        [
          55.458844900131226,
          318.1587829589844
        ]
      ]
    },
    {
      "title": "5.2. Energ\u00b4\u0131a y trabajo de un fluido fluyendo",
      "heading_level": null,
      "page_id": 64,
      "polygon": [
        [
          55.413302063941956,
          489.15484619140625
        ],
        [
          378.15619468688965,
          489.15484619140625
        ],
        [
          378.15619468688965,
          503.50103759765625
        ],
        [
          55.413302063941956,
          503.50103759765625
        ]
      ]
    },
    {
      "title": "5.2.1. Flujo de Trabajo",
      "heading_level": null,
      "page_id": 64,
      "polygon": [
        [
          55.70819056034088,
          516.1224975585938
        ],
        [
          201.46525633335114,
          516.1224975585938
        ],
        [
          201.46525633335114,
          528.334098815918
        ],
        [
          55.70819056034088,
          528.334098815918
        ]
      ]
    },
    {
      "title": "",
      "heading_level": null,
      "page_id": 65,
      "polygon": [
        [
          5.05432690680027,
          193.07492995262146
        ],
        [
          45.362616419792175,
          193.07492995262146
        ],
        [
          44.167303919792175,
          202.9393265247345
        ],
        [
          3.85901440680027,
          202.9393265247345
        ]
      ]
    },
    {
      "title": "5.2.2. Flujo de energ\u00b4\u0131a total de un fluido",
      "heading_level": null,
      "page_id": 65,
      "polygon": [
        [
          56.37305760383606,
          231.1036376953125
        ],
        [
          303.4961853027344,
          231.1036376953125
        ],
        [
          303.4961853027344,
          243.6445198059082
        ],
        [
          56.37305760383606,
          243.6445198059082
        ]
      ]
    },
    {
      "title": "5.3. An\u00b4alisis de energ\u00b4\u0131a de un sistema con flujo constante.",
      "heading_level": null,
      "page_id": 65,
      "polygon": [
        [
          56.307068824768066,
          589.7529602050781
        ],
        [
          477.9036512374878,
          589.7529602050781
        ],
        [
          476.7083387374878,
          604.0991516113281
        ],
        [
          55.111756324768066,
          604.5247263908386
        ]
      ]
    },
    {
      "title": "5.3.1. Algunas maquinas de flujo estacionario",
      "heading_level": null,
      "page_id": 67,
      "polygon": [
        [
          56.03590929508209,
          156.83062744140625
        ],
        [
          332.49290800094604,
          156.83062744140625
        ],
        [
          331.29759550094604,
          168.78582763671875
        ],
        [
          54.84059679508209,
          168.78582763671875
        ]
      ]
    },
    {
      "title": "Toberas y Difusores",
      "heading_level": null,
      "page_id": 67,
      "polygon": [
        [
          56.6696058511734,
          178.47021484375
        ],
        [
          167.07747852802277,
          177.8580286502838
        ],
        [
          165.88216602802277,
          189.37933349609375
        ],
        [
          55.4742933511734,
          189.37933349609375
        ]
      ]
    },
    {
      "title": "Turbinas y Compresores",
      "heading_level": null,
      "page_id": 67,
      "polygon": [
        [
          56.693031311035156,
          506.9661865234375
        ],
        [
          191.1093589067459,
          506.9661865234375
        ],
        [
          191.1093589067459,
          517.8753051757812
        ],
        [
          56.693031311035156,
          517.8753051757812
        ]
      ]
    },
    {
      "title": "V\u00b4alvula de Paso",
      "heading_level": null,
      "page_id": 68,
      "polygon": [
        [
          55.7221342921257,
          164.61313569545746
        ],
        [
          145.514892578125,
          164.61313569545746
        ],
        [
          145.514892578125,
          175.8292236328125
        ],
        [
          55.7221342921257,
          175.8292236328125
        ]
      ]
    },
    {
      "title": "C\u00b4amara de Mezcla",
      "heading_level": null,
      "page_id": 68,
      "polygon": [
        [
          55.89537763595581,
          513.7592468261719
        ],
        [
          159.31175923347473,
          513.057858467102
        ],
        [
          159.31175923347473,
          524.6683654785156
        ],
        [
          55.89537763595581,
          524.6683654785156
        ]
      ]
    },
    {
      "title": "Intercambiador de calor",
      "heading_level": null,
      "page_id": 69,
      "polygon": [
        [
          56.692996978759766,
          87.37693476676941
        ],
        [
          188.21311950683594,
          87.37693476676941
        ],
        [
          188.21311950683594,
          98.41588568687439
        ],
        [
          55.581187695264816,
          98.41588568687439
        ]
      ]
    },
    {
      "title": "Tuber\u00b4\u0131a y ducto de flujo",
      "heading_level": null,
      "page_id": 70,
      "polygon": [
        [
          56.33899167180061,
          87.27915161848068
        ],
        [
          190.55100774765015,
          87.27915161848068
        ],
        [
          189.83856201171875,
          98.44798046350479
        ],
        [
          55.14367917180061,
          98.44798046350479
        ]
      ]
    },
    {
      "title": "5.4. An\u00b4alisis de energ\u00b4\u0131a de un flujo transiente",
      "heading_level": null,
      "page_id": 70,
      "polygon": [
        [
          56.097575426101685,
          311.8680114746094
        ],
        [
          388.70455026626587,
          311.8680114746094
        ],
        [
          387.50923776626587,
          326.42244243621826
        ],
        [
          54.902262926101685,
          326.42244243621826
        ]
      ]
    },
    {
      "title": "Ejemplos",
      "heading_level": null,
      "page_id": 72,
      "polygon": [
        [
          56.03862690925598,
          84.78594970703125
        ],
        [
          121.50929009914398,
          84.78594970703125
        ],
        [
          120.8635482788086,
          99.1322021484375
        ],
        [
          54.84331440925598,
          99.1322021484375
        ]
      ]
    }
  ],
  "page_stats": [
    {
      "page_id": 0,
      "text_extraction_method": "pdftext",
      "block_counts": [
        [
          "Span",
          3
        ],
        [
          "Line",
          2
        ],
        [
          "SectionHeader",
          1
        ],
        [
          "Text",
          1
        ]
      ],
      "block_metadata": {
        "llm_request_count": 0,
        "llm_error_count": 0,
        "llm_tokens_used": 0
      }
    },
    {
      "page_id": 1,
      "text_extraction_method": "pdftext",
      "block_counts": [
        [
          "Text",
          1
        ]
      ],
      "block_metadata": {
        "llm_request_count": 0,
        "llm_error_count": 0,
        "llm_tokens_used": 0
      }
    },
    {
      "page_id": 2,
      "text_extraction_method": "pdftext",
      "block_counts": [
        [
          "Span",
          12
        ],
        [
          "Line",
          7
        ],
        [
          "Text",
          2
        ],
        [
          "SectionHeader",
          1
        ],
        [
          "PageFooter",
          1
        ],
        [
          "Reference",
          1
        ]
      ],
      "block_metadata": {
        "llm_request_count": 0,
        "llm_error_count": 0,
        "llm_tokens_used": 0
      }
    },
    {
      "page_id": 3,
      "text_extraction_method": "pdftext",
      "block_counts": [
        [
          "Span",
          179
        ],
        [
          "TableCell",
          115
        ],
        [
          "Line",
          33
        ],
        [
          "SectionHeader",
          1
        ],
        [
          "TableOfContents",
          1
        ],
        [
          "PageFooter",
          1
        ]
      ],
      "block_metadata": {
        "llm_request_count": 0,
        "llm_error_count": 0,
        "llm_tokens_used": 0
      }
    },
    {
      "page_id": 4,
      "text_extraction_method": "pdftext",
      "block_counts": [
        [
          "Span",
          209
        ],
        [
          "TableCell",
          132
        ],
        [
          "Line",
          35
        ],
        [
          "TableOfContents",
          1
        ],
        [
          "PageFooter",
          1
        ]
      ],
      "block_metadata": {
        "llm_request_count": 0,
        "llm_error_count": 0,
        "llm_tokens_used": 0
      }
    },
    {
      "page_id": 5,
      "text_extraction_method": "pdftext",
      "block_counts": [
        [
          "Span",
          143
        ],
        [
          "Line",
          37
        ],
        [
          "Text",
          6
        ],
        [
          "SectionHeader",
          5
        ],
        [
          "Reference",
          4
        ],
        [
          "Equation",
          3
        ],
        [
          "PageFooter",
          1
        ]
      ],
      "block_metadata": {
        "llm_request_count": 0,
        "llm_error_count": 0,
        "llm_tokens_used": 0
      }
    },
    {
      "page_id": 6,
      "text_extraction_method": "pdftext",
      "block_counts": [
        [
          "Span",
          105
        ],
        [
          "Line",
          34
        ],
        [
          "Text",
          6
        ],
        [
          "ListItem",
          5
        ],
        [
          "ListGroup",
          2
        ],
        [
          "Figure",
          1
        ],
        [
          "Caption",
          1
        ],
        [
          "TextInlineMath",
          1
        ],
        [
          "PageFooter",
          1
        ],
        [
          "FigureGroup",
          1
        ]
      ],
      "block_metadata": {
        "llm_request_count": 0,
        "llm_error_count": 0,
        "llm_tokens_used": 0
      }
    },
    {
      "page_id": 7,
      "text_extraction_method": "pdftext",
      "block_counts": [
        [
          "Span",
          106
        ],
        [
          "Line",
          40
        ],
        [
          "Text",
          9
        ],
        [
          "Equation",
          4
        ],
        [
          "Reference",
          3
        ],
        [
          "SectionHeader",
          2
        ],
        [
          "Figure",
          1
        ],
        [
          "Caption",
          1
        ],
        [
          "PageFooter",
          1
        ],
        [
          "FigureGroup",
          1
        ]
      ],
      "block_metadata": {
        "llm_request_count": 0,
        "llm_error_count": 0,
        "llm_tokens_used": 0
      }
    },
    {
      "page_id": 8,
      "text_extraction_method": "pdftext",
      "block_counts": [
        [
          "Span",
          108
        ],
        [
          "Line",
          28
        ],
        [
          "Text",
          7
        ],
        [
          "ListItem",
          4
        ],
        [
          "SectionHeader",
          3
        ],
        [
          "Figure",
          1
        ],
        [
          "Caption",
          1
        ],
        [
          "PageFooter",
          1
        ],
        [
          "FigureGroup",
          1
        ],
        [
          "ListGroup",
          1
        ],
        [
          "Reference",
          1
        ]
      ],
      "block_metadata": {
        "llm_request_count": 0,
        "llm_error_count": 0,
        "llm_tokens_used": 0
      }
    },
    {
      "page_id": 9,
      "text_extraction_method": "pdftext",
      "block_counts": [
        [
          "Span",
          290
        ],
        [
          "Line",
          42
        ],
        [
          "Text",
          5
        ],
        [
          "Equation",
          5
        ],
        [
          "TextInlineMath",
          3
        ],
        [
          "Figure",
          1
        ],
        [
          "Caption",
          1
        ],
        [
          "PageFooter",
          1
        ],
        [
          "FigureGroup",
          1
        ],
        [
          "Reference",
          1
        ]
      ],
      "block_metadata": {
        "llm_request_count": 0,
        "llm_error_count": 0,
        "llm_tokens_used": 0
      }
    },
    {
      "page_id": 10,
      "text_extraction_method": "pdftext",
      "block_counts": [
        [
          "Span",
          143
        ],
        [
          "Line",
          32
        ],
        [
          "Text",
          10
        ],
        [
          "Equation",
          5
        ],
        [
          "Reference",
          3
        ],
        [
          "SectionHeader",
          2
        ],
        [
          "Figure",
          1
        ],
        [
          "Caption",
          1
        ],
        [
          "PageFooter",
          1
        ],
        [
          "FigureGroup",
          1
        ]
      ],
      "block_metadata": {
        "llm_request_count": 0,
        "llm_error_count": 0,
        "llm_tokens_used": 0
      }
    },
    {
      "page_id": 11,
      "text_extraction_method": "pdftext",
      "block_counts": [
        [
          "Span",
          142
        ],
        [
          "Line",
          34
        ],
        [
          "Text",
          7
        ],
        [
          "SectionHeader",
          3
        ],
        [
          "Equation",
          3
        ],
        [
          "Reference",
          3
        ],
        [
          "Figure",
          1
        ],
        [
          "TextInlineMath",
          1
        ],
        [
          "PageFooter",
          1
        ]
      ],
      "block_metadata": {
        "llm_request_count": 0,
        "llm_error_count": 0,
        "llm_tokens_used": 0
      }
    },
    {
      "page_id": 12,
      "text_extraction_method": "pdftext",
      "block_counts": [
        [
          "Span",
          142
        ],
        [
          "Line",
          30
        ],
        [
          "Text",
          8
        ],
        [
          "Equation",
          3
        ],
        [
          "Reference",
          3
        ],
        [
          "SectionHeader",
          2
        ],
        [
          "Figure",
          1
        ],
        [
          "Footnote",
          1
        ],
        [
          "PageFooter",
          1
        ]
      ],
      "block_metadata": {
        "llm_request_count": 0,
        "llm_error_count": 0,
        "llm_tokens_used": 0
      }
    },
    {
      "page_id": 13,
      "text_extraction_method": "pdftext",
      "block_counts": [
        [
          "Span",
          242
        ],
        [
          "Line",
          40
        ],
        [
          "Text",
          7
        ],
        [
          "Equation",
          3
        ],
        [
          "Reference",
          3
        ],
        [
          "SectionHeader",
          2
        ],
        [
          "TextInlineMath",
          2
        ],
        [
          "Figure",
          2
        ],
        [
          "PageFooter",
          1
        ]
      ],
      "block_metadata": {
        "llm_request_count": 0,
        "llm_error_count": 0,
        "llm_tokens_used": 0
      }
    },
    {
      "page_id": 14,
      "text_extraction_method": "pdftext",
      "block_counts": [
        [
          "Span",
          286
        ],
        [
          "Line",
          33
        ],
        [
          "Text",
          9
        ],
        [
          "Equation",
          7
        ],
        [
          "ListItem",
          2
        ],
        [
          "TextInlineMath",
          2
        ],
        [
          "Figure",
          1
        ],
        [
          "Caption",
          1
        ],
        [
          "PageFooter",
          1
        ],
        [
          "FigureGroup",
          1
        ],
        [
          "Reference",
          1
        ]
      ],
      "block_metadata": {
        "llm_request_count": 0,
        "llm_error_count": 0,
        "llm_tokens_used": 0
      }
    },
    {
      "page_id": 15,
      "text_extraction_method": "pdftext",
      "block_counts": [
        [
          "Span",
          331
        ],
        [
          "Line",
          65
        ],
        [
          "Text",
          7
        ],
        [
          "Equation",
          6
        ],
        [
          "ListItem",
          4
        ],
        [
          "Figure",
          1
        ],
        [
          "SectionHeader",
          1
        ],
        [
          "PageFooter",
          1
        ],
        [
          "ListGroup",
          1
        ],
        [
          "Reference",
          1
        ]
      ],
      "block_metadata": {
        "llm_request_count": 0,
        "llm_error_count": 0,
        "llm_tokens_used": 0
      }
    },
    {
      "page_id": 16,
      "text_extraction_method": "pdftext",
      "block_counts": [
        [
          "Span",
          285
        ],
        [
          "Line",
          42
        ],
        [
          "Equation",
          6
        ],
        [
          "ListItem",
          5
        ],
        [
          "Text",
          4
        ],
        [
          "TextInlineMath",
          4
        ],
        [
          "PageFooter",
          1
        ],
        [
          "ListGroup",
          1
        ]
      ],
      "block_metadata": {
        "llm_request_count": 0,
        "llm_error_count": 0,
        "llm_tokens_used": 0
      }
    },
    {
      "page_id": 17,
      "text_extraction_method": "pdftext",
      "block_counts": [
        [
          "Span",
          190
        ],
        [
          "Line",
          45
        ],
        [
          "Text",
          6
        ],
        [
          "SectionHeader",
          3
        ],
        [
          "Equation",
          3
        ],
        [
          "TextInlineMath",
          2
        ],
        [
          "Reference",
          2
        ],
        [
          "PageFooter",
          1
        ]
      ],
      "block_metadata": {
        "llm_request_count": 0,
        "llm_error_count": 0,
        "llm_tokens_used": 0
      }
    },
    {
      "page_id": 18,
      "text_extraction_method": "pdftext",
      "block_counts": [
        [
          "Span",
          246
        ],
        [
          "Line",
          68
        ],
        [
          "Text",
          9
        ],
        [
          "Equation",
          5
        ],
        [
          "ListItem",
          2
        ],
        [
          "SectionHeader",
          2
        ],
        [
          "Reference",
          2
        ],
        [
          "TextInlineMath",
          1
        ],
        [
          "PageFooter",
          1
        ],
        [
          "ListGroup",
          1
        ]
      ],
      "block_metadata": {
        "llm_request_count": 0,
        "llm_error_count": 0,
        "llm_tokens_used": 0
      }
    },
    {
      "page_id": 19,
      "text_extraction_method": "pdftext",
      "block_counts": [
        [
          "Span",
          187
        ],
        [
          "Line",
          40
        ],
        [
          "Text",
          9
        ],
        [
          "Equation",
          4
        ],
        [
          "Reference",
          3
        ],
        [
          "TextInlineMath",
          2
        ],
        [
          "Figure",
          1
        ],
        [
          "Caption",
          1
        ],
        [
          "SectionHeader",
          1
        ],
        [
          "FigureGroup",
          1
        ]
      ],
      "block_metadata": {
        "llm_request_count": 0,
        "llm_error_count": 0,
        "llm_tokens_used": 0
      }
    },
    {
      "page_id": 20,
      "text_extraction_method": "pdftext",
      "block_counts": [
        [
          "Span",
          271
        ],
        [
          "Line",
          52
        ],
        [
          "Text",
          8
        ],
        [
          "Equation",
          7
        ],
        [
          "SectionHeader",
          3
        ],
        [
          "TextInlineMath",
          2
        ],
        [
          "PageFooter",
          1
        ],
        [
          "Reference",
          1
        ]
      ],
      "block_metadata": {
        "llm_request_count": 0,
        "llm_error_count": 0,
        "llm_tokens_used": 0
      }
    },
    {
      "page_id": 21,
      "text_extraction_method": "pdftext",
      "block_counts": [
        [
          "Span",
          335
        ],
        [
          "Line",
          62
        ],
        [
          "Text",
          7
        ],
        [
          "Equation",
          7
        ],
        [
          "TextInlineMath",
          2
        ],
        [
          "SectionHeader",
          2
        ],
        [
          "PageFooter",
          1
        ]
      ],
      "block_metadata": {
        "llm_request_count": 0,
        "llm_error_count": 0,
        "llm_tokens_used": 0
      }
    },
    {
      "page_id": 22,
      "text_extraction_method": "pdftext",
      "block_counts": [
        [
          "Span",
          217
        ],
        [
          "Line",
          46
        ],
        [
          "Text",
          6
        ],
        [
          "Equation",
          5
        ],
        [
          "Reference",
          5
        ],
        [
          "SectionHeader",
          3
        ],
        [
          "Figure",
          1
        ],
        [
          "Caption",
          1
        ],
        [
          "TextInlineMath",
          1
        ],
        [
          "Footnote",
          1
        ],
        [
          "PageFooter",
          1
        ],
        [
          "FigureGroup",
          1
        ]
      ],
      "block_metadata": {
        "llm_request_count": 0,
        "llm_error_count": 0,
        "llm_tokens_used": 0
      }
    },
    {
      "page_id": 23,
      "text_extraction_method": "pdftext",
      "block_counts": [
        [
          "Span",
          144
        ],
        [
          "Line",
          34
        ],
        [
          "Text",
          10
        ],
        [
          "Equation",
          5
        ],
        [
          "SectionHeader",
          1
        ],
        [
          "TextInlineMath",
          1
        ],
        [
          "Figure",
          1
        ],
        [
          "PageFooter",
          1
        ],
        [
          "Reference",
          1
        ]
      ],
      "block_metadata": {
        "llm_request_count": 0,
        "llm_error_count": 0,
        "llm_tokens_used": 0
      }
    },
    {
      "page_id": 24,
      "text_extraction_method": "pdftext",
      "block_counts": [
        [
          "Span",
          187
        ],
        [
          "Line",
          43
        ],
        [
          "Text",
          9
        ],
        [
          "Equation",
          6
        ],
        [
          "SectionHeader",
          2
        ],
        [
          "PageFooter",
          1
        ],
        [
          "Reference",
          1
        ]
      ],
      "block_metadata": {
        "llm_request_count": 0,
        "llm_error_count": 0,
        "llm_tokens_used": 0
      }
    },
    {
      "page_id": 25,
      "text_extraction_method": "pdftext",
      "block_counts": [
        [
          "Span",
          214
        ],
        [
          "Line",
          45
        ],
        [
          "Text",
          8
        ],
        [
          "Equation",
          4
        ],
        [
          "ListItem",
          4
        ],
        [
          "TextInlineMath",
          2
        ],
        [
          "Figure",
          1
        ],
        [
          "Caption",
          1
        ],
        [
          "PageFooter",
          1
        ],
        [
          "FigureGroup",
          1
        ],
        [
          "ListGroup",
          1
        ],
        [
          "Reference",
          1
        ]
      ],
      "block_metadata": {
        "llm_request_count": 0,
        "llm_error_count": 0,
        "llm_tokens_used": 0
      }
    },
    {
      "page_id": 26,
      "text_extraction_method": "pdftext",
      "block_counts": [
        [
          "Span",
          231
        ],
        [
          "Line",
          46
        ],
        [
          "Text",
          9
        ],
        [
          "Equation",
          7
        ],
        [
          "ListItem",
          2
        ],
        [
          "SectionHeader",
          1
        ],
        [
          "PageFooter",
          1
        ],
        [
          "ListGroup",
          1
        ],
        [
          "Reference",
          1
        ]
      ],
      "block_metadata": {
        "llm_request_count": 0,
        "llm_error_count": 0,
        "llm_tokens_used": 0
      }
    },
    {
      "page_id": 27,
      "text_extraction_method": "pdftext",
      "block_counts": [
        [
          "Span",
          354
        ],
        [
          "Line",
          89
        ],
        [
          "Equation",
          8
        ],
        [
          "Text",
          6
        ],
        [
          "TextInlineMath",
          2
        ],
        [
          "Figure",
          1
        ],
        [
          "PageFooter",
          1
        ]
      ],
      "block_metadata": {
        "llm_request_count": 0,
        "llm_error_count": 0,
        "llm_tokens_used": 0
      }
    },
    {
      "page_id": 28,
      "text_extraction_method": "pdftext",
      "block_counts": [
        [
          "Span",
          195
        ],
        [
          "Line",
          45
        ],
        [
          "Text",
          5
        ],
        [
          "Equation",
          4
        ],
        [
          "ListItem",
          2
        ],
        [
          "Figure",
          1
        ],
        [
          "TextInlineMath",
          1
        ],
        [
          "PageFooter",
          1
        ],
        [
          "ListGroup",
          1
        ]
      ],
      "block_metadata": {
        "llm_request_count": 0,
        "llm_error_count": 0,
        "llm_tokens_used": 0
      }
    },
    {
      "page_id": 29,
      "text_extraction_method": "pdftext",
      "block_counts": [
        [
          "Span",
          352
        ],
        [
          "Line",
          65
        ],
        [
          "Text",
          9
        ],
        [
          "Equation",
          9
        ],
        [
          "ListItem",
          4
        ],
        [
          "TextInlineMath",
          2
        ],
        [
          "ListGroup",
          2
        ],
        [
          "PageFooter",
          1
        ]
      ],
      "block_metadata": {
        "llm_request_count": 0,
        "llm_error_count": 0,
        "llm_tokens_used": 0
      }
    },
    {
      "page_id": 30,
      "text_extraction_method": "pdftext",
      "block_counts": [
        [
          "Span",
          148
        ],
        [
          "Line",
          24
        ],
        [
          "Figure",
          2
        ],
        [
          "TextInlineMath",
          2
        ],
        [
          "Text",
          2
        ],
        [
          "Equation",
          2
        ],
        [
          "SectionHeader",
          1
        ],
        [
          "PageFooter",
          1
        ],
        [
          "Reference",
          1
        ]
      ],
      "block_metadata": {
        "llm_request_count": 0,
        "llm_error_count": 0,
        "llm_tokens_used": 0
      }
    },
    {
      "page_id": 31,
      "text_extraction_method": "pdftext",
      "block_counts": [
        [
          "Span",
          75
        ],
        [
          "Line",
          28
        ],
        [
          "SectionHeader",
          5
        ],
        [
          "Text",
          4
        ],
        [
          "Reference",
          4
        ],
        [
          "PageFooter",
          1
        ]
      ],
      "block_metadata": {
        "llm_request_count": 0,
        "llm_error_count": 0,
        "llm_tokens_used": 0
      }
    },
    {
      "page_id": 32,
      "text_extraction_method": "pdftext",
      "block_counts": [
        [
          "Span",
          136
        ],
        [
          "Line",
          30
        ],
        [
          "Text",
          7
        ],
        [
          "PageFooter",
          2
        ],
        [
          "Reference",
          2
        ],
        [
          "SectionHeader",
          1
        ],
        [
          "Figure",
          1
        ],
        [
          "Caption",
          1
        ],
        [
          "TextInlineMath",
          1
        ],
        [
          "FigureGroup",
          1
        ]
      ],
      "block_metadata": {
        "llm_request_count": 0,
        "llm_error_count": 0,
        "llm_tokens_used": 0
      }
    },
    {
      "page_id": 33,
      "text_extraction_method": "pdftext",
      "block_counts": [
        [
          "Span",
          49
        ],
        [
          "Line",
          16
        ],
        [
          "Text",
          5
        ],
        [
          "Figure",
          3
        ],
        [
          "Caption",
          2
        ],
        [
          "FigureGroup",
          2
        ],
        [
          "Reference",
          2
        ],
        [
          "PageFooter",
          1
        ]
      ],
      "block_metadata": {
        "llm_request_count": 0,
        "llm_error_count": 0,
        "llm_tokens_used": 0
      }
    },
    {
      "page_id": 34,
      "text_extraction_method": "pdftext",
      "block_counts": [
        [
          "Span",
          103
        ],
        [
          "Line",
          26
        ],
        [
          "Text",
          5
        ],
        [
          "Reference",
          3
        ],
        [
          "SectionHeader",
          2
        ],
        [
          "PageFooter",
          2
        ],
        [
          "Figure",
          1
        ],
        [
          "Caption",
          1
        ],
        [
          "FigureGroup",
          1
        ]
      ],
      "block_metadata": {
        "llm_request_count": 0,
        "llm_error_count": 0,
        "llm_tokens_used": 0
      }
    },
    {
      "page_id": 35,
      "text_extraction_method": "pdftext",
      "block_counts": [
        [
          "Span",
          68
        ],
        [
          "Line",
          10
        ],
        [
          "Figure",
          4
        ],
        [
          "Text",
          3
        ],
        [
          "Reference",
          3
        ],
        [
          "Caption",
          1
        ],
        [
          "SectionHeader",
          1
        ],
        [
          "PageFooter",
          1
        ],
        [
          "FigureGroup",
          1
        ]
      ],
      "block_metadata": {
        "llm_request_count": 0,
        "llm_error_count": 0,
        "llm_tokens_used": 0
      }
    },
    {
      "page_id": 36,
      "text_extraction_method": "pdftext",
      "block_counts": [
        [
          "Span",
          75
        ],
        [
          "Line",
          14
        ],
        [
          "Figure",
          3
        ],
        [
          "Reference",
          3
        ],
        [
          "Text",
          2
        ],
        [
          "Caption",
          1
        ],
        [
          "SectionHeader",
          1
        ],
        [
          "PageFooter",
          1
        ],
        [
          "FigureGroup",
          1
        ]
      ],
      "block_metadata": {
        "llm_request_count": 0,
        "llm_error_count": 0,
        "llm_tokens_used": 0
      }
    },
    {
      "page_id": 37,
      "text_extraction_method": "pdftext",
      "block_counts": [
        [
          "Span",
          82
        ],
        [
          "TableCell",
          58
        ],
        [
          "Line",
          21
        ],
        [
          "Text",
          6
        ],
        [
          "Equation",
          3
        ],
        [
          "ListItem",
          2
        ],
        [
          "Reference",
          2
        ],
        [
          "SectionHeader",
          1
        ],
        [
          "Table",
          1
        ],
        [
          "Caption",
          1
        ],
        [
          "PageFooter",
          1
        ],
        [
          "TableGroup",
          1
        ],
        [
          "ListGroup",
          1
        ]
      ],
      "block_metadata": {
        "llm_request_count": 0,
        "llm_error_count": 0,
        "llm_tokens_used": 0
      }
    },
    {
      "page_id": 38,
      "text_extraction_method": "pdftext",
      "block_counts": [
        [
          "Span",
          118
        ],
        [
          "Line",
          17
        ],
        [
          "Text",
          7
        ],
        [
          "Equation",
          3
        ],
        [
          "Figure",
          2
        ],
        [
          "ListItem",
          1
        ],
        [
          "Caption",
          1
        ],
        [
          "PageFooter",
          1
        ],
        [
          "Reference",
          1
        ]
      ],
      "block_metadata": {
        "llm_request_count": 0,
        "llm_error_count": 0,
        "llm_tokens_used": 0
      }
    },
    {
      "page_id": 39,
      "text_extraction_method": "pdftext",
      "block_counts": [
        [
          "Span",
          199
        ],
        [
          "Line",
          28
        ],
        [
          "Text",
          7
        ],
        [
          "Equation",
          5
        ],
        [
          "ListItem",
          2
        ],
        [
          "TextInlineMath",
          1
        ],
        [
          "Figure",
          1
        ],
        [
          "SectionHeader",
          1
        ],
        [
          "PageFooter",
          1
        ],
        [
          "ListGroup",
          1
        ],
        [
          "Reference",
          1
        ]
      ],
      "block_metadata": {
        "llm_request_count": 0,
        "llm_error_count": 0,
        "llm_tokens_used": 0
      }
    },
    {
      "page_id": 40,
      "text_extraction_method": "pdftext",
      "block_counts": [
        [
          "Span",
          249
        ],
        [
          "Line",
          33
        ],
        [
          "Equation",
          7
        ],
        [
          "Text",
          5
        ],
        [
          "TextInlineMath",
          4
        ],
        [
          "Picture",
          1
        ],
        [
          "Caption",
          1
        ],
        [
          "PageFooter",
          1
        ],
        [
          "PictureGroup",
          1
        ],
        [
          "Reference",
          1
        ]
      ],
      "block_metadata": {
        "llm_request_count": 0,
        "llm_error_count": 0,
        "llm_tokens_used": 0
      }
    },
    {
      "page_id": 41,
      "text_extraction_method": "pdftext",
      "block_counts": [
        [
          "Span",
          180
        ],
        [
          "Line",
          36
        ],
        [
          "Text",
          9
        ],
        [
          "Equation",
          6
        ],
        [
          "ListItem",
          2
        ],
        [
          "Figure",
          1
        ],
        [
          "Caption",
          1
        ],
        [
          "PageFooter",
          1
        ],
        [
          "FigureGroup",
          1
        ],
        [
          "ListGroup",
          1
        ],
        [
          "Reference",
          1
        ]
      ],
      "block_metadata": {
        "llm_request_count": 0,
        "llm_error_count": 0,
        "llm_tokens_used": 0
      }
    },
    {
      "page_id": 42,
      "text_extraction_method": "pdftext",
      "block_counts": [
        [
          "Span",
          265
        ],
        [
          "Line",
          49
        ],
        [
          "Text",
          9
        ],
        [
          "Equation",
          7
        ],
        [
          "ListItem",
          4
        ],
        [
          "TextInlineMath",
          2
        ],
        [
          "PageFooter",
          1
        ],
        [
          "ListGroup",
          1
        ]
      ],
      "block_metadata": {
        "llm_request_count": 0,
        "llm_error_count": 0,
        "llm_tokens_used": 0
      }
    },
    {
      "page_id": 43,
      "text_extraction_method": "pdftext",
      "block_counts": [
        [
          "TableCell",
          254
        ],
        [
          "Span",
          159
        ],
        [
          "Line",
          26
        ],
        [
          "ListItem",
          5
        ],
        [
          "SectionHeader",
          2
        ],
        [
          "TextInlineMath",
          2
        ],
        [
          "Text",
          2
        ],
        [
          "Reference",
          2
        ],
        [
          "Table",
          1
        ],
        [
          "PageFooter",
          1
        ],
        [
          "ListGroup",
          1
        ]
      ],
      "block_metadata": {
        "llm_request_count": 0,
        "llm_error_count": 0,
        "llm_tokens_used": 0
      }
    },
    {
      "page_id": 44,
      "text_extraction_method": "pdftext",
      "block_counts": [
        [
          "Span",
          261
        ],
        [
          "Line",
          50
        ],
        [
          "Equation",
          6
        ],
        [
          "Text",
          6
        ],
        [
          "TextInlineMath",
          3
        ],
        [
          "Reference",
          3
        ],
        [
          "SectionHeader",
          2
        ],
        [
          "Footnote",
          1
        ],
        [
          "PageFooter",
          1
        ]
      ],
      "block_metadata": {
        "llm_request_count": 0,
        "llm_error_count": 0,
        "llm_tokens_used": 0
      }
    },
    {
      "page_id": 45,
      "text_extraction_method": "pdftext",
      "block_counts": [
        [
          "Span",
          283
        ],
        [
          "Line",
          46
        ],
        [
          "Text",
          10
        ],
        [
          "Equation",
          8
        ],
        [
          "TextInlineMath",
          2
        ],
        [
          "PageFooter",
          1
        ]
      ],
      "block_metadata": {
        "llm_request_count": 0,
        "llm_error_count": 0,
        "llm_tokens_used": 0
      }
    },
    {
      "page_id": 46,
      "text_extraction_method": "pdftext",
      "block_counts": [
        [
          "Span",
          84
        ],
        [
          "Line",
          28
        ],
        [
          "Text",
          6
        ],
        [
          "Equation",
          2
        ],
        [
          "Figure",
          2
        ],
        [
          "Caption",
          1
        ],
        [
          "PageFooter",
          1
        ],
        [
          "FigureGroup",
          1
        ],
        [
          "Reference",
          1
        ]
      ],
      "block_metadata": {
        "llm_request_count": 0,
        "llm_error_count": 0,
        "llm_tokens_used": 0
      }
    },
    {
      "page_id": 47,
      "text_extraction_method": "pdftext",
      "block_counts": [
        [
          "Span",
          109
        ],
        [
          "Line",
          23
        ],
        [
          "Text",
          2
        ],
        [
          "ListItem",
          2
        ],
        [
          "Figure",
          1
        ],
        [
          "Caption",
          1
        ],
        [
          "Equation",
          1
        ],
        [
          "TextInlineMath",
          1
        ],
        [
          "PageFooter",
          1
        ],
        [
          "FigureGroup",
          1
        ],
        [
          "ListGroup",
          1
        ],
        [
          "Reference",
          1
        ]
      ],
      "block_metadata": {
        "llm_request_count": 0,
        "llm_error_count": 0,
        "llm_tokens_used": 0
      }
    },
    {
      "page_id": 48,
      "text_extraction_method": "pdftext",
      "block_counts": [
        [
          "Span",
          240
        ],
        [
          "Line",
          58
        ],
        [
          "Text",
          10
        ],
        [
          "Equation",
          6
        ],
        [
          "ListItem",
          3
        ],
        [
          "PageFooter",
          1
        ],
        [
          "ListGroup",
          1
        ]
      ],
      "block_metadata": {
        "llm_request_count": 0,
        "llm_error_count": 0,
        "llm_tokens_used": 0
      }
    },
    {
      "page_id": 49,
      "text_extraction_method": "pdftext",
      "block_counts": [
        [
          "Span",
          112
        ],
        [
          "Line",
          24
        ],
        [
          "Text",
          5
        ],
        [
          "SectionHeader",
          3
        ],
        [
          "Reference",
          3
        ],
        [
          "Equation",
          2
        ],
        [
          "TextInlineMath",
          1
        ],
        [
          "Picture",
          1
        ],
        [
          "Caption",
          1
        ],
        [
          "PageFooter",
          1
        ]
      ],
      "block_metadata": {
        "llm_request_count": 0,
        "llm_error_count": 0,
        "llm_tokens_used": 0
      }
    },
    {
      "page_id": 50,
      "text_extraction_method": "pdftext",
      "block_counts": [
        [
          "Span",
          384
        ],
        [
          "Line",
          90
        ],
        [
          "Equation",
          8
        ],
        [
          "Text",
          7
        ],
        [
          "TextInlineMath",
          4
        ],
        [
          "ListItem",
          3
        ],
        [
          "SectionHeader",
          1
        ],
        [
          "PageFooter",
          1
        ],
        [
          "ListGroup",
          1
        ],
        [
          "Reference",
          1
        ]
      ],
      "block_metadata": {
        "llm_request_count": 0,
        "llm_error_count": 0,
        "llm_tokens_used": 0
      }
    },
    {
      "page_id": 51,
      "text_extraction_method": "pdftext",
      "block_counts": [
        [
          "Span",
          165
        ],
        [
          "Line",
          28
        ],
        [
          "Text",
          8
        ],
        [
          "Equation",
          6
        ],
        [
          "ListItem",
          3
        ],
        [
          "SectionHeader",
          1
        ],
        [
          "Figure",
          1
        ],
        [
          "PageFooter",
          1
        ],
        [
          "ListGroup",
          1
        ],
        [
          "Reference",
          1
        ]
      ],
      "block_metadata": {
        "llm_request_count": 0,
        "llm_error_count": 0,
        "llm_tokens_used": 0
      }
    },
    {
      "page_id": 52,
      "text_extraction_method": "pdftext",
      "block_counts": [
        [
          "Span",
          300
        ],
        [
          "Line",
          48
        ],
        [
          "Text",
          13
        ],
        [
          "Equation",
          12
        ],
        [
          "TextInlineMath",
          1
        ],
        [
          "PageFooter",
          1
        ]
      ],
      "block_metadata": {
        "llm_request_count": 0,
        "llm_error_count": 0,
        "llm_tokens_used": 0
      }
    },
    {
      "page_id": 53,
      "text_extraction_method": "pdftext",
      "block_counts": [
        [
          "Span",
          285
        ],
        [
          "Line",
          49
        ],
        [
          "Text",
          9
        ],
        [
          "Equation",
          7
        ],
        [
          "TextInlineMath",
          3
        ],
        [
          "SectionHeader",
          2
        ],
        [
          "ListItem",
          1
        ],
        [
          "PageFooter",
          1
        ],
        [
          "Reference",
          1
        ]
      ],
      "block_metadata": {
        "llm_request_count": 0,
        "llm_error_count": 0,
        "llm_tokens_used": 0
      }
    },
    {
      "page_id": 54,
      "text_extraction_method": "pdftext",
      "block_counts": [
        [
          "Span",
          85
        ],
        [
          "Line",
          22
        ],
        [
          "Equation",
          2
        ],
        [
          "Text",
          2
        ],
        [
          "TextInlineMath",
          1
        ],
        [
          "PageFooter",
          1
        ]
      ],
      "block_metadata": {
        "llm_request_count": 0,
        "llm_error_count": 0,
        "llm_tokens_used": 0
      }
    },
    {
      "page_id": 55,
      "text_extraction_method": "pdftext",
      "block_counts": [
        [
          "Span",
          291
        ],
        [
          "Line",
          52
        ],
        [
          "Equation",
          9
        ],
        [
          "Text",
          8
        ],
        [
          "TextInlineMath",
          2
        ],
        [
          "Reference",
          2
        ],
        [
          "SectionHeader",
          1
        ],
        [
          "Footnote",
          1
        ],
        [
          "PageFooter",
          1
        ]
      ],
      "block_metadata": {
        "llm_request_count": 0,
        "llm_error_count": 0,
        "llm_tokens_used": 0
      }
    },
    {
      "page_id": 56,
      "text_extraction_method": "pdftext",
      "block_counts": [
        [
          "Span",
          331
        ],
        [
          "Line",
          45
        ],
        [
          "Text",
          9
        ],
        [
          "Equation",
          8
        ],
        [
          "TextInlineMath",
          2
        ],
        [
          "Reference",
          2
        ],
        [
          "SectionHeader",
          1
        ],
        [
          "Footnote",
          1
        ],
        [
          "PageFooter",
          1
        ]
      ],
      "block_metadata": {
        "llm_request_count": 0,
        "llm_error_count": 0,
        "llm_tokens_used": 0
      }
    },
    {
      "page_id": 57,
      "text_extraction_method": "pdftext",
      "block_counts": [
        [
          "Span",
          219
        ],
        [
          "Line",
          26
        ],
        [
          "Text",
          10
        ],
        [
          "Equation",
          7
        ],
        [
          "ListItem",
          3
        ],
        [
          "SectionHeader",
          1
        ],
        [
          "PageFooter",
          1
        ],
        [
          "ListGroup",
          1
        ],
        [
          "Reference",
          1
        ]
      ],
      "block_metadata": {
        "llm_request_count": 0,
        "llm_error_count": 0,
        "llm_tokens_used": 0
      }
    },
    {
      "page_id": 58,
      "text_extraction_method": "pdftext",
      "block_counts": [
        [
          "Span",
          245
        ],
        [
          "Line",
          51
        ],
        [
          "Text",
          10
        ],
        [
          "Equation",
          9
        ],
        [
          "SectionHeader",
          1
        ],
        [
          "TextInlineMath",
          1
        ],
        [
          "PageFooter",
          1
        ],
        [
          "Reference",
          1
        ]
      ],
      "block_metadata": {
        "llm_request_count": 0,
        "llm_error_count": 0,
        "llm_tokens_used": 0
      }
    },
    {
      "page_id": 59,
      "text_extraction_method": "pdftext",
      "block_counts": [
        [
          "Span",
          348
        ],
        [
          "Line",
          42
        ],
        [
          "Equation",
          8
        ],
        [
          "Text",
          5
        ],
        [
          "TextInlineMath",
          3
        ],
        [
          "ListItem",
          3
        ],
        [
          "Figure",
          1
        ],
        [
          "PageFooter",
          1
        ],
        [
          "ListGroup",
          1
        ]
      ],
      "block_metadata": {
        "llm_request_count": 0,
        "llm_error_count": 0,
        "llm_tokens_used": 0
      }
    },
    {
      "page_id": 60,
      "text_extraction_method": "pdftext",
      "block_counts": [
        [
          "Span",
          324
        ],
        [
          "Line",
          34
        ],
        [
          "Text",
          7
        ],
        [
          "Equation",
          6
        ],
        [
          "ListItem",
          5
        ],
        [
          "Figure",
          1
        ],
        [
          "PageFooter",
          1
        ],
        [
          "ListGroup",
          1
        ]
      ],
      "block_metadata": {
        "llm_request_count": 0,
        "llm_error_count": 0,
        "llm_tokens_used": 0
      }
    },
    {
      "page_id": 61,
      "text_extraction_method": "pdftext",
      "block_counts": [
        [
          "Span",
          130
        ],
        [
          "Line",
          35
        ],
        [
          "Text",
          6
        ],
        [
          "Reference",
          5
        ],
        [
          "SectionHeader",
          4
        ],
        [
          "Equation",
          3
        ],
        [
          "TextInlineMath",
          1
        ],
        [
          "Footnote",
          1
        ],
        [
          "PageFooter",
          1
        ]
      ],
      "block_metadata": {
        "llm_request_count": 0,
        "llm_error_count": 0,
        "llm_tokens_used": 0
      }
    },
    {
      "page_id": 62,
      "text_extraction_method": "pdftext",
      "block_counts": [
        [
          "Span",
          189
        ],
        [
          "Line",
          34
        ],
        [
          "Text",
          5
        ],
        [
          "Equation",
          3
        ],
        [
          "Figure",
          2
        ],
        [
          "Caption",
          2
        ],
        [
          "FigureGroup",
          2
        ],
        [
          "Reference",
          2
        ],
        [
          "TextInlineMath",
          1
        ],
        [
          "PageFooter",
          1
        ]
      ],
      "block_metadata": {
        "llm_request_count": 0,
        "llm_error_count": 0,
        "llm_tokens_used": 0
      }
    },
    {
      "page_id": 63,
      "text_extraction_method": "pdftext",
      "block_counts": [
        [
          "Span",
          201
        ],
        [
          "Line",
          39
        ],
        [
          "Text",
          7
        ],
        [
          "Equation",
          7
        ],
        [
          "Reference",
          3
        ],
        [
          "Figure",
          2
        ],
        [
          "SectionHeader",
          1
        ],
        [
          "TextInlineMath",
          1
        ],
        [
          "PageFooter",
          1
        ]
      ],
      "block_metadata": {
        "llm_request_count": 0,
        "llm_error_count": 0,
        "llm_tokens_used": 0
      }
    },
    {
      "page_id": 64,
      "text_extraction_method": "pdftext",
      "block_counts": [
        [
          "Span",
          263
        ],
        [
          "Line",
          61
        ],
        [
          "Text",
          11
        ],
        [
          "Equation",
          9
        ],
        [
          "SectionHeader",
          3
        ],
        [
          "Reference",
          3
        ],
        [
          "PageFooter",
          1
        ]
      ],
      "block_metadata": {
        "llm_request_count": 0,
        "llm_error_count": 0,
        "llm_tokens_used": 0
      }
    },
    {
      "page_id": 65,
      "text_extraction_method": "pdftext",
      "block_counts": [
        [
          "Span",
          158
        ],
        [
          "Line",
          37
        ],
        [
          "Text",
          9
        ],
        [
          "Equation",
          5
        ],
        [
          "SectionHeader",
          3
        ],
        [
          "Reference",
          3
        ],
        [
          "Figure",
          1
        ],
        [
          "Caption",
          1
        ],
        [
          "PageFooter",
          1
        ],
        [
          "FigureGroup",
          1
        ]
      ],
      "block_metadata": {
        "llm_request_count": 0,
        "llm_error_count": 0,
        "llm_tokens_used": 0
      }
    },
    {
      "page_id": 66,
      "text_extraction_method": "pdftext",
      "block_counts": [
        [
          "Span",
          275
        ],
        [
          "Line",
          83
        ],
        [
          "Text",
          5
        ],
        [
          "ListItem",
          5
        ],
        [
          "Equation",
          4
        ],
        [
          "TextInlineMath",
          2
        ],
        [
          "Caption",
          2
        ],
        [
          "ListGroup",
          2
        ],
        [
          "Figure",
          1
        ],
        [
          "PageFooter",
          1
        ],
        [
          "Reference",
          1
        ]
      ],
      "block_metadata": {
        "llm_request_count": 0,
        "llm_error_count": 0,
        "llm_tokens_used": 0
      }
    },
    {
      "page_id": 67,
      "text_extraction_method": "pdftext",
      "block_counts": [
        [
          "Span",
          119
        ],
        [
          "Line",
          29
        ],
        [
          "Text",
          8
        ],
        [
          "SectionHeader",
          3
        ],
        [
          "Reference",
          2
        ],
        [
          "Figure",
          1
        ],
        [
          "Caption",
          1
        ],
        [
          "ListItem",
          1
        ],
        [
          "PageFooter",
          1
        ],
        [
          "FigureGroup",
          1
        ]
      ],
      "block_metadata": {
        "llm_request_count": 0,
        "llm_error_count": 0,
        "llm_tokens_used": 0
      }
    },
    {
      "page_id": 68,
      "text_extraction_method": "pdftext",
      "block_counts": [
        [
          "Span",
          190
        ],
        [
          "Line",
          35
        ],
        [
          "Text",
          11
        ],
        [
          "ListItem",
          7
        ],
        [
          "Equation",
          3
        ],
        [
          "TextInlineMath",
          3
        ],
        [
          "SectionHeader",
          2
        ],
        [
          "ListGroup",
          2
        ],
        [
          "PageFooter",
          1
        ]
      ],
      "block_metadata": {
        "llm_request_count": 0,
        "llm_error_count": 0,
        "llm_tokens_used": 0
      }
    },
    {
      "page_id": 69,
      "text_extraction_method": "pdftext",
      "block_counts": [
        [
          "Span",
          77
        ],
        [
          "Line",
          16
        ],
        [
          "Text",
          5
        ],
        [
          "Figure",
          4
        ],
        [
          "ListItem",
          3
        ],
        [
          "Reference",
          2
        ],
        [
          "SectionHeader",
          1
        ],
        [
          "ListGroup",
          1
        ]
      ],
      "block_metadata": {
        "llm_request_count": 0,
        "llm_error_count": 0,
        "llm_tokens_used": 0
      }
    },
    {
      "page_id": 70,
      "text_extraction_method": "pdftext",
      "block_counts": [
        [
          "Span",
          116
        ],
        [
          "Line",
          35
        ],
        [
          "Text",
          9
        ],
        [
          "ListItem",
          9
        ],
        [
          "SectionHeader",
          2
        ],
        [
          "Equation",
          2
        ],
        [
          "ListGroup",
          2
        ],
        [
          "PageFooter",
          1
        ],
        [
          "Reference",
          1
        ]
      ],
      "block_metadata": {
        "llm_request_count": 0,
        "llm_error_count": 0,
        "llm_tokens_used": 0
      }
    },
    {
      "page_id": 71,
      "text_extraction_method": "pdftext",
      "block_counts": [
        [
          "Span",
          257
        ],
        [
          "Line",
          48
        ],
        [
          "Text",
          10
        ],
        [
          "ListItem",
          9
        ],
        [
          "Equation",
          3
        ],
        [
          "ListGroup",
          3
        ],
        [
          "TextInlineMath",
          1
        ],
        [
          "PageFooter",
          1
        ]
      ],
      "block_metadata": {
        "llm_request_count": 0,
        "llm_error_count": 0,
        "llm_tokens_used": 0
      }
    },
    {
      "page_id": 72,
      "text_extraction_method": "pdftext",
      "block_counts": [
        [
          "Span",
          247
        ],
        [
          "Line",
          55
        ],
        [
          "Text",
          6
        ],
        [
          "Equation",
          5
        ],
        [
          "ListItem",
          2
        ],
        [
          "TextInlineMath",
          2
        ],
        [
          "Figure",
          2
        ],
        [
          "SectionHeader",
          1
        ],
        [
          "PageFooter",
          1
        ],
        [
          "ListGroup",
          1
        ],
        [
          "Reference",
          1
        ]
      ],
      "block_metadata": {
        "llm_request_count": 0,
        "llm_error_count": 0,
        "llm_tokens_used": 0
      }
    },
    {
      "page_id": 73,
      "text_extraction_method": "pdftext",
      "block_counts": [
        [
          "Span",
          215
        ],
        [
          "Line",
          47
        ],
        [
          "Text",
          5
        ],
        [
          "Equation",
          4
        ],
        [
          "ListItem",
          3
        ],
        [
          "Caption",
          2
        ],
        [
          "Figure",
          1
        ],
        [
          "TextInlineMath",
          1
        ],
        [
          "PageFooter",
          1
        ],
        [
          "ListGroup",
          1
        ],
        [
          "Reference",
          1
        ]
      ],
      "block_metadata": {
        "llm_request_count": 0,
        "llm_error_count": 0,
        "llm_tokens_used": 0
      }
    },
    {
      "page_id": 74,
      "text_extraction_method": "pdftext",
      "block_counts": [
        [
          "Span",
          257
        ],
        [
          "Line",
          39
        ],
        [
          "Text",
          7
        ],
        [
          "Equation",
          6
        ],
        [
          "TextInlineMath",
          2
        ],
        [
          "ListItem",
          2
        ],
        [
          "Figure",
          1
        ],
        [
          "PageFooter",
          1
        ],
        [
          "ListGroup",
          1
        ]
      ],
      "block_metadata": {
        "llm_request_count": 0,
        "llm_error_count": 0,
        "llm_tokens_used": 0
      }
    },
    {
      "page_id": 75,
      "text_extraction_method": "pdftext",
      "block_counts": [
        [
          "Span",
          112
        ],
        [
          "Line",
          17
        ],
        [
          "Equation",
          6
        ],
        [
          "Text",
          3
        ],
        [
          "TextInlineMath",
          1
        ],
        [
          "PageFooter",
          1
        ]
      ],
      "block_metadata": {
        "llm_request_count": 0,
        "llm_error_count": 0,
        "llm_tokens_used": 0
      }
    }
  ],
  "debug_data_path": "debug_data/Termodinamica"
}